LICENSE
MANIFEST.in
README.rst
requirements.txt
setup.py
Hipshot.egg-info/PKG-INFO
Hipshot.egg-info/SOURCES.txt
Hipshot.egg-info/dependency_links.txt
Hipshot.egg-info/requires.txt
Hipshot.egg-info/top_level.txt
hipshot/__init__.py
hipshot/hipshot.py
scripts/hipshot