Metadata-Version: 1.1
Name: Hipshot
Version: 0.9
Summary: Hipshot converts a video file or series of photographs into
